pandaemonium/CHANGES
pandaemonium/LICENSE
pandaemonium/__init__.py
pandaemonium-0.9.1.dist-info/METADATA
pandaemonium-0.9.1.dist-info/WHEEL
pandaemonium-0.9.1.dist-info/top_level.txt
pandaemonium-0.9.1.dist-info/RECORD
